bitfuncs/__init__.py
bitfuncs/constants.py
bitfuncs/decorators.py
bitfuncs/helpers.py
bitfuncs/queries.py
bitfuncs/settings.py
bitfuncs/contrib/__init__.py
bitfuncs/contrib/backtesting/__init__.py
bitfuncs/contrib/backtesting/strategies.py
bitfuncs/contrib/bittrex/__init__.py
bitfuncs/contrib/bittrex/connector.py
bitfuncs/contrib/degiro/__init__.py
bitfuncs/contrib/degiro/chart_parser.py
bitfuncs/contrib/degiro/connector.py
bitfuncs/contrib/degiro/constants.py
bitfuncs/contrib/yahoo/__init__.py
bitfuncs/contrib/yahoo/chart_parser.py
bitfuncs/contrib/yahoo/connector.py
bitfuncs/contrib/yahoo/constants.py
bitfuncs/funcs/__init__.py
bitfuncs/funcs/backtesting.py
bitfuncs/funcs/common.py
bitfuncs/funcs/db.py
bitfuncs/models/__init__.py
bitfuncs/models/base.py
bitfuncs/models/indicators.py
bitfuncs/models/values.py
bitfuncs-0.2.0.dist-info/LICENSE
bitfuncs-0.2.0.dist-info/METADATA
bitfuncs-0.2.0.dist-info/WHEEL
bitfuncs-0.2.0.dist-info/top_level.txt
bitfuncs-0.2.0.dist-info/zip-safe
bitfuncs-0.2.0.dist-info/RECORD
