Metadata-Version: 2.1
Name: bitfuncs
Version: 0.2.0
Summary: Some async funcs for trading.
Home-page: https://gitlab.com/toopy/bitfuncs
Author: Florent Pigout
Author-email: florent@toopy.org
License: MIT
Keywords: async,functions,trading
Classifier: Development Status :: 4 - Beta
Classifier: Intended Audience :: Developers
Classifier: License :: OSI Approved :: MIT License
Classifier: Natural Language :: English
Classifier: Programming Language :: Python :: 3.8
License-File: LICENSE
Requires-Dist: aiocache[redis]
Requires-Dist: asyncsql
Requires-Dist: chamallow
Requires-Dist: dynaconf
Provides-Extra: backtest
Requires-Dist: TA-Lib (==0.4.24) ; extra == 'backtest'
Requires-Dist: backtesting ; extra == 'backtest'
Requires-Dist: numpy ; extra == 'backtest'
Requires-Dist: pandas (<1.2) ; extra == 'backtest'
Provides-Extra: bittrex
Requires-Dist: aiobittrex ; extra == 'bittrex'
Provides-Extra: degiro
Requires-Dist: degiro-connector ; extra == 'degiro'
Provides-Extra: lint
Requires-Dist: black ; extra == 'lint'
Requires-Dist: flake8 ; extra == 'lint'
Requires-Dist: isort ; extra == 'lint'
Requires-Dist: pre-commit ; extra == 'lint'
Provides-Extra: plot
Requires-Dist: matplotlib (==3.2.2) ; extra == 'plot'
Provides-Extra: release
Requires-Dist: wheel[signatures] ; extra == 'release'
Requires-Dist: zest.releaser ; extra == 'release'
Provides-Extra: test
Requires-Dist: async-generator ; extra == 'test'
Requires-Dist: pytest ; extra == 'test'
Requires-Dist: pytest-asyncio ; extra == 'test'
Requires-Dist: pytest-cov ; extra == 'test'
Requires-Dist: pytest-lazy-fixture ; extra == 'test'
Requires-Dist: pytest-mock ; extra == 'test'
Provides-Extra: yahoo
Requires-Dist: yfinance ; extra == 'yahoo'
Provides-Extra: zipline
Requires-Dist: zipline-reloaded ; extra == 'zipline'
